Metadata-Version: 2.4
Name: biobb_structure_checking
Version: 3.15.6
Summary: BioBB_structure_checking performs MDWeb structure checking tool set as a command line utility.
Home-page: https://github.com/bioexcel/biobb_structure_checking
Author: Biobb developers
Author-email: gelpi@ub.edu
Project-URL: Documentation, http://BioBB_structure_checking.readthedocs.io/en/latest/
Project-URL: Bioexcel, https://bioexcel.eu/
Keywords: Bioinformatics Workflows BioExcel Compatibility
Classifier: Development Status :: 3 - Alpha
Classifier: Programming Language :: Python :: 3
Classifier: License :: OSI Approved :: Apache Software License
Classifier: Operating System :: MacOS :: MacOS X
Classifier: Operating System :: POSIX
Requires-Python: >=3.8
License-File: LICENSE
Requires-Dist: psutil
Requires-Dist: numpy
Requires-Dist: biopython>=1.79
Dynamic: author
Dynamic: author-email
Dynamic: classifier
Dynamic: description
Dynamic: description-content-type
Dynamic: home-page
Dynamic: keywords
Dynamic: license-file
Dynamic: project-url
Dynamic: requires-dist
Dynamic: requires-python
Dynamic: summary
